menu_cli_seb/__init__.py
menu_cli_seb/__main__.py
menu_cli_seb/main.py
menu_cli_seb/properties.py
menu_cli_seb-0.1.6.dist-info/entry_points.txt
menu_cli_seb-0.1.6.dist-info/METADATA
menu_cli_seb-0.1.6.dist-info/WHEEL
menu_cli_seb-0.1.6.dist-info/RECORD
